odoo/addons/sm_partago_invoicing/__init__.py
odoo/addons/sm_partago_invoicing/__manifest__.py
odoo/addons/sm_partago_invoicing/demo/demo_data.xml
odoo/addons/sm_partago_invoicing/email_tmpl/invoice_email.xml
odoo/addons/sm_partago_invoicing/email_tmpl/invoice_report.xml
odoo/addons/sm_partago_invoicing/email_tmpl/sale_order.xml
odoo/addons/sm_partago_invoicing/models/__init__.py
odoo/addons/sm_partago_invoicing/models/batch_type_enum.py
odoo/addons/sm_partago_invoicing/models/models_cs_task.py
odoo/addons/sm_partago_invoicing/models/models_reservation_calculator.py
odoo/addons/sm_partago_invoicing/models/models_sm_company.py
odoo/addons/sm_partago_invoicing/models/models_sm_invoice.py
odoo/addons/sm_partago_invoicing/models/models_sm_invoice_line.py
odoo/addons/sm_partago_invoicing/models/models_sm_invoice_report.py
odoo/addons/sm_partago_invoicing/models/models_sm_invoice_report_wizard.py
odoo/addons/sm_partago_invoicing/models/models_sm_member.py
odoo/addons/sm_partago_invoicing/models/models_sm_res_config_settings.py
odoo/addons/sm_partago_invoicing/models/models_smp_batch_reservation_compute.py
odoo/addons/sm_partago_invoicing/models/models_smp_batch_reservation_compute_wizard.py
odoo/addons/sm_partago_invoicing/models/models_smp_report_reservation_compute.py
odoo/addons/sm_partago_invoicing/models/models_smp_reservation_compute.py
odoo/addons/sm_partago_invoicing/models/models_smp_teletac.py
odoo/addons/sm_partago_invoicing/report/contact.xml
odoo/addons/sm_partago_invoicing/report/invoice_report.xml
odoo/addons/sm_partago_invoicing/report/sm_invoice_report.xml
odoo/addons/sm_partago_invoicing/security/ir.model.access.csv
odoo/addons/sm_partago_invoicing/services/__init__.py
odoo/addons/sm_partago_invoicing/services/invoice_services.py
odoo/addons/sm_partago_invoicing/services/report_services.py
odoo/addons/sm_partago_invoicing/static/src/js/base.js
odoo/addons/sm_partago_invoicing/static/src/xml/base.xml
odoo/addons/sm_partago_invoicing/views/views.xml
odoo12_addon_sm_partago_invoicing-12.0.0.1.16.dist-info/METADATA
odoo12_addon_sm_partago_invoicing-12.0.0.1.16.dist-info/WHEEL
odoo12_addon_sm_partago_invoicing-12.0.0.1.16.dist-info/top_level.txt
odoo12_addon_sm_partago_invoicing-12.0.0.1.16.dist-info/RECORD
